django_mock_queries/__init__.py
django_mock_queries/asserts.py
django_mock_queries/comparisons.py
django_mock_queries/constants.py
django_mock_queries/exceptions.py
django_mock_queries/mocks.py
django_mock_queries/query.py
django_mock_queries/utils.py
django_mock_queries-2.3.0.dist-info/LICENSE.txt
django_mock_queries-2.3.0.dist-info/METADATA
django_mock_queries-2.3.0.dist-info/WHEEL
django_mock_queries-2.3.0.dist-info/top_level.txt
django_mock_queries-2.3.0.dist-info/RECORD
