Metadata-Version: 2.1
Name: django_mock_queries
Version: 2.3.0
Summary: A django library for mocking queryset functions in memory for testing
Home-page: https://github.com/stphivos/django-mock-queries
Author: Phivos Stylianides
Author-email: stphivos@gmail.com
License: MIT
Keywords: django orm mocking unit-testing tdd
Classifier: Development Status :: 5 - Production/Stable
Classifier: Intended Audience :: Developers
Classifier: Topic :: Software Development :: Testing
Classifier: Topic :: Software Development :: Testing :: Mocking
Classifier: Topic :: Software Development :: Testing :: Unit
Classifier: License :: OSI Approved :: MIT License
Classifier: Programming Language :: Python
Classifier: Programming Language :: Python :: 3 :: Only
License-File: LICENSE.txt
Requires-Dist: Django
Requires-Dist: djangorestframework
Requires-Dist: model-bakery >=1.0.0
